django_run_context/__init__.py
django_run_context-1.0.dist-info/licenses/LICENSE.md
django_run_context-1.0.dist-info/METADATA
django_run_context-1.0.dist-info/WHEEL
django_run_context-1.0.dist-info/top_level.txt
django_run_context-1.0.dist-info/RECORD
