Metadata-Version: 2.3
Name: django_run_context
Version: 1.0
Summary: Detetermine the context under which a Django project is run (provides a get_run_context function)
Home-page: https://github.com/bernd-wechner/django-run-context
Author: Bernd Wechner
Author-email: bwechner@yahoo.com
Project-URL: Bug Tracker, https://github.com/bernd-wechner/django-run-context/issues
Classifier: Programming Language :: Python :: 3
Classifier: License :: Freely Distributable
Classifier: Operating System :: OS Independent
Classifier: Development Status :: 5 - Production/Stable
Classifier: Framework :: Django :: 5.1
Classifier: Intended Audience :: System Administrators
Classifier: Topic :: Internet :: WWW/HTTP :: HTTP Servers
Requires-Python: >=3.7
License-File: LICENSE.md
Dynamic: license-file
